sqlexceller/__init__.py
sqlexceller/sqlexceller.py
sqlexceller-0.1.1.dist-info/DESCRIPTION.rst
sqlexceller-0.1.1.dist-info/METADATA
sqlexceller-0.1.1.dist-info/RECORD
sqlexceller-0.1.1.dist-info/WHEEL
sqlexceller-0.1.1.dist-info/entry_points.txt
sqlexceller-0.1.1.dist-info/metadata.json
sqlexceller-0.1.1.dist-info/top_level.txt
