Metadata-Version: 2.0
Name: sqlexceller
Version: 0.1.1
Summary: Command line program that executes SQL queries and stores results in Excel files
Home-page: https://github.com/akrog/sqlexceller
Author: Gorka Eguileor
Author-email: gorka@eguileor.com
License: Apache Software License 2.0
Keywords: sqlexceller
Platform: UNKNOWN
Classifier: Development Status :: 2 - Pre-Alpha
Classifier: Intended Audience :: Developers
Classifier: License :: OSI Approved :: Apache Software License
Classifier: Natural Language :: English
Classifier: Programming Language :: Python :: 2
Classifier: Programming Language :: Python :: 2.7
Classifier: Programming Language :: Python :: 3
Classifier: Programming Language :: Python :: 3.3
Classifier: Programming Language :: Python :: 3.4
Classifier: Programming Language :: Python :: 3.5
Requires-Dist: openpyxl
Requires-Dist: six
Requires-Dist: sqlalchemy
